flask_sekazi.py
Flask_Sekazi-0.0.3.dist-info/LICENSE.txt
Flask_Sekazi-0.0.3.dist-info/METADATA
Flask_Sekazi-0.0.3.dist-info/WHEEL
Flask_Sekazi-0.0.3.dist-info/top_level.txt
Flask_Sekazi-0.0.3.dist-info/RECORD
